{
  "metainfo" : {
    "id" : "1",
    "language" : "python",
    "fabricId" : "382",
    "frontEndLanguage" : "sql",
    "mode" : "batch",
    "udfs" : {
      "language" : "python",
      "udfs" : [ ]
    },
    "udafs" : {
      "language" : "python",
      "code" : ""
    },
    "configuration" : {
      "common" : {
        "type" : "record",
        "fields" : [ ]
      },
      "fabrics" : {
        "dev" : {
          "type" : "record",
          "fields" : [ ]
        },
        "test" : {
          "type" : "record",
          "fields" : [ ]
        },
        "Remove" : {
          "type" : "record",
          "fields" : [ ]
        },
        "demos" : {
          "type" : "record",
          "fields" : [ ]
        }
      }
    },
    "sparkConf" : [ ],
    "hadoopConf" : [ ],
    "codeMode" : "sparse",
    "buildSystem" : "maven",
    "externalDependencies" : [ ],
    "isImported" : false,
    "interimMode" : "Full",
    "interimModeEnabled" : true,
    "visualCodeInterimMode" : "Disabled",
    "recordsLimit" : {
      "enabled" : false,
      "value" : 1000
    }
  },
  "connections" : [ {
    "id" : "6Nh4Vt3W076VeEL18hjm7",
    "source" : "Yy6pP8lhFguYKvFwdBPf5$$dJoN3lF8FUG0zZ1lAlyvo",
    "sourcePort" : "spNCjsQL_v_WKeDkteX-8$$NtyM7qBgs4dLr_WdBEFtm",
    "target" : "CcQ378yKaOzliNXblEhYx$$h8weA19Uiih2DyMJtQVt0",
    "targetPort" : "xmelSzkbtvAQTQAgE8ves$$TTsxKQLXXu-S7xopECZ8f"
  }, {
    "id" : "wHOpGCqEroSx8zZ-gL39W",
    "source" : "CcQ378yKaOzliNXblEhYx$$h8weA19Uiih2DyMJtQVt0",
    "sourcePort" : "HAUtAbwgu7kkpEiW6hsMH$$5-M_mLQUTKvwGUpZ5Ge1f",
    "target" : "QqtGtL3X1JFIp-flRGAh1$$kQLX0lwsJLBfIhfHf1kzD",
    "targetPort" : "mqaOUPDJE_ADROKSWpAkf$$MEslioeZBYwVZF3kdgf04"
  }, {
    "id" : "XjE70Me5pnIPKMVbrTpeP",
    "source" : "_GiFXBzO_NnB4iIsyRM0T$$V8hemfRGNZuQVK4vHELdK",
    "sourcePort" : "ASJRyxNpCf6bMQdv5RZh1$$s58ROYh4qPn1zeTNghc6q",
    "target" : "gbYKKVua7scDsVkSKtFE8$$Y0_hCWCy5Dl_zyms6nVrV",
    "targetPort" : "ugvkLH5Fj7DnYs1CtAGkw$$PfnTlqZEIeNhhvI_xm_Q2"
  }, {
    "id" : "-L6ODHS8sO2ZA37dFIZKk",
    "source" : "gbYKKVua7scDsVkSKtFE8$$Y0_hCWCy5Dl_zyms6nVrV",
    "sourcePort" : "C6NN-uJzKFv_alsKPoJ6c$$ViQLSFjvbJqKhN2mLQDk-",
    "target" : "bpXu-Hun__7xIF_ykAqNA$$LrzKw7EPIzlJ9wMkK8cz1",
    "targetPort" : "GSKYD4-HPLz-kWKlzwT2g$$KOxmJHOOzzPO4BJYP-lxp"
  }, {
    "id" : "H6ioAv_azpIbkv5jEpHE5",
    "source" : "QqtGtL3X1JFIp-flRGAh1$$kQLX0lwsJLBfIhfHf1kzD",
    "sourcePort" : "lG7Ij5kEpCXIPRklmewCq$$Etg4Ll5zrdPLNUEVQRzFS",
    "target" : "1We4nap3dEhZx6jjdSw6u$$wfYl839GDVV8zzysC92rk",
    "targetPort" : "93T_Zw67QiXsuEhY3ApeY$$GEvLmT4bD7S5A0Ohpy95N"
  }, {
    "id" : "604btYIlW3W8pu45Q6Ffd",
    "source" : "1We4nap3dEhZx6jjdSw6u$$wfYl839GDVV8zzysC92rk",
    "sourcePort" : "MRUyDBUS0qgyLUkBI_s5m$$lQY_DepJ0XJVmoEGHNBQr",
    "target" : "BKfj7FhwIUo51cPDED1cV$$ERdTXAT-w1Yun4TCeHWOy",
    "targetPort" : "siHiegQWwyVZNHVnS1StX$$xjDz2VyuAxzke47tLAtD5"
  }, {
    "id" : "W-r0hYbf8tBitiVtAt61g",
    "source" : "GEejzfFJwhhRdwk6Q-PCh$$m66deH1Tyg9stGeTup4Gh",
    "sourcePort" : "xFGKSTeNlfbVJZgH5xwx5$$ZkYYqTJMbV4SJEhXTTMgZ",
    "target" : "cwGenY4Qa5QOIhzy14O0R$$pgJniJ2bYsvfJaNOxbae5",
    "targetPort" : "Ma2Cgxy1KRJQ5cRs6lAsh$$L31qIcSVrbn4zgZvrOtUe"
  }, {
    "id" : "ISz0SAHQh5lviw0r3lJ4c",
    "source" : "GEejzfFJwhhRdwk6Q-PCh$$m66deH1Tyg9stGeTup4Gh",
    "sourcePort" : "xFGKSTeNlfbVJZgH5xwx5$$ZkYYqTJMbV4SJEhXTTMgZ",
    "target" : "H4qeKZuWDPLa5xc8Ze_-S$$RP_O-g7nIFI-SH4PT-Tkx",
    "targetPort" : "mB-uZB0ld2WC6LuApYt9p$$ntncYtMS8Zo2P9vamjLb9"
  }, {
    "id" : "-omcI2ILG-bz78cv9uagM",
    "source" : "bpXu-Hun__7xIF_ykAqNA$$LrzKw7EPIzlJ9wMkK8cz1",
    "sourcePort" : "Tzk3MdIhZx3ETbh1nfEYz$$fa1TBFNkhPpBZati5Zuca",
    "target" : "GEejzfFJwhhRdwk6Q-PCh$$m66deH1Tyg9stGeTup4Gh",
    "targetPort" : "NZ0kHuT74qGojFDCTTHE8$$rsqxbUvcyPwiOwYSLVymr"
  }, {
    "id" : "5GeFy2k-tckEMlQsaxj1n",
    "source" : "_GiFXBzO_NnB4iIsyRM0T$$V8hemfRGNZuQVK4vHELdK",
    "sourcePort" : "ASJRyxNpCf6bMQdv5RZh1$$s58ROYh4qPn1zeTNghc6q",
    "target" : "LqTTU_Ra4CXT7mwQJnGGS$$VSAqz4qDtlkjt-kMoFlYM",
    "targetPort" : "O1fBdsvrjWl1FU6vAvnur$$UAwatZ9YI1kQpvG85BYtM"
  }, {
    "id" : "fIWTygULFdTAJ9Md2uHHE",
    "source" : "LqTTU_Ra4CXT7mwQJnGGS$$VSAqz4qDtlkjt-kMoFlYM",
    "sourcePort" : "GPWfwdfNVB7IQaSFRcY_G$$9vDuUBGv6OHIEjy3htNsa",
    "target" : "jb9duRCS8hF5CRSE7nBqS$$HbGSX3XWqWSTcnCBlR6RI",
    "targetPort" : "VpSIP4oZ4h-rA_gNmZYEU$$dK8WoT-C6r2A6nEQaCsls"
  } ],
  "processes" : {
    "gbYKKVua7scDsVkSKtFE8$$Y0_hCWCy5Dl_zyms6nVrV" : {
      "id" : "gbYKKVua7scDsVkSKtFE8$$Y0_hCWCy5Dl_zyms6nVrV",
      "component" : "Reformat",
      "metadata" : {
        "label" : "Reformat_2",
        "slug" : "Reformat_2",
        "x" : 718.3,
        "y" : 448.00000000000006,
        "language" : "python",
        "phase" : 0,
        "cache" : false,
        "detailedStats" : false,
        "isImported" : false
      },
      "ports" : {
        "inputs" : [ {
          "id" : "ugvkLH5Fj7DnYs1CtAGkw$$PfnTlqZEIeNhhvI_xm_Q2",
          "slug" : "in0"
        } ],
        "outputs" : [ {
          "id" : "C6NN-uJzKFv_alsKPoJ6c$$ViQLSFjvbJqKhN2mLQDk-",
          "slug" : "out"
        } ],
        "selectedInputFields" : [ ],
        "isCustomOutputSchema" : false
      },
      "properties" : {
        "columnsSelector" : [ ],
        "expressions" : [ ]
      }
    },
    "Yy6pP8lhFguYKvFwdBPf5$$dJoN3lF8FUG0zZ1lAlyvo" : {
      "id" : "Yy6pP8lhFguYKvFwdBPf5$$dJoN3lF8FUG0zZ1lAlyvo",
      "component" : "Source",
      "metadata" : {
        "label" : "FarmersMarketsSource",
        "slug" : "FarmersMarketsSource",
        "x" : 487,
        "y" : 214,
        "language" : "python",
        "phase" : 0,
        "cache" : false,
        "detailedStats" : false,
        "isImported" : false
      },
      "ports" : {
        "inputs" : [ ],
        "outputs" : [ {
          "id" : "spNCjsQL_v_WKeDkteX-8$$NtyM7qBgs4dLr_WdBEFtm",
          "slug" : "out"
        } ],
        "selectedInputFields" : [ ],
        "isCustomOutputSchema" : false
      },
      "properties" : {
        "datasetId" : "1700/datasets/farmers-markets"
      }
    },
    "CcQ378yKaOzliNXblEhYx$$h8weA19Uiih2DyMJtQVt0" : {
      "id" : "CcQ378yKaOzliNXblEhYx$$h8weA19Uiih2DyMJtQVt0",
      "component" : "Filter",
      "metadata" : {
        "label" : "Filter_1",
        "slug" : "Filter_1",
        "x" : 690,
        "y" : 218,
        "language" : "python",
        "phase" : 0,
        "cache" : false,
        "detailedStats" : false,
        "isImported" : false
      },
      "ports" : {
        "inputs" : [ {
          "id" : "xmelSzkbtvAQTQAgE8ves$$TTsxKQLXXu-S7xopECZ8f",
          "slug" : "in0"
        } ],
        "outputs" : [ {
          "id" : "HAUtAbwgu7kkpEiW6hsMH$$5-M_mLQUTKvwGUpZ5Ge1f",
          "slug" : "out"
        } ],
        "selectedInputFields" : [ ],
        "isCustomOutputSchema" : false
      },
      "properties" : {
        "columnsSelector" : [ "xmelSzkbtvAQTQAgE8ves$$TTsxKQLXXu-S7xopECZ8f##zip" ],
        "condition" : {
          "format" : "sql",
          "expression" : "zip is not null"
        }
      }
    },
    "jb9duRCS8hF5CRSE7nBqS$$HbGSX3XWqWSTcnCBlR6RI" : {
      "id" : "jb9duRCS8hF5CRSE7nBqS$$HbGSX3XWqWSTcnCBlR6RI",
      "component" : "Filter",
      "metadata" : {
        "label" : "Filter_2",
        "slug" : "Filter_2",
        "x" : 1014.3250000000004,
        "y" : 694.1499999999999,
        "language" : "python",
        "phase" : 0,
        "cache" : false,
        "detailedStats" : false,
        "isImported" : false
      },
      "ports" : {
        "inputs" : [ {
          "id" : "VpSIP4oZ4h-rA_gNmZYEU$$dK8WoT-C6r2A6nEQaCsls",
          "slug" : "in0"
        } ],
        "outputs" : [ {
          "id" : "djCc69J9McMK57E_fLVYO$$dLY4QlyCvNLXu5eidC0XP",
          "slug" : "out"
        } ],
        "selectedInputFields" : [ ],
        "isCustomOutputSchema" : false
      },
      "properties" : {
        "columnsSelector" : [ ],
        "condition" : {
          "format" : "sql",
          "expression" : "true"
        }
      }
    },
    "GEejzfFJwhhRdwk6Q-PCh$$m66deH1Tyg9stGeTup4Gh" : {
      "id" : "GEejzfFJwhhRdwk6Q-PCh$$m66deH1Tyg9stGeTup4Gh",
      "component" : "Reformat",
      "metadata" : {
        "label" : "Reformat_3",
        "slug" : "Reformat_3",
        "x" : 1148.3000000000002,
        "y" : 426.00000000000006,
        "language" : "python",
        "phase" : 0,
        "cache" : false,
        "detailedStats" : false,
        "isImported" : false
      },
      "ports" : {
        "inputs" : [ {
          "id" : "NZ0kHuT74qGojFDCTTHE8$$rsqxbUvcyPwiOwYSLVymr",
          "slug" : "in0"
        } ],
        "outputs" : [ {
          "id" : "xFGKSTeNlfbVJZgH5xwx5$$ZkYYqTJMbV4SJEhXTTMgZ",
          "slug" : "out"
        } ],
        "selectedInputFields" : [ ],
        "isCustomOutputSchema" : false
      },
      "properties" : {
        "columnsSelector" : [ ],
        "expressions" : [ ]
      }
    },
    "QqtGtL3X1JFIp-flRGAh1$$kQLX0lwsJLBfIhfHf1kzD" : {
      "id" : "QqtGtL3X1JFIp-flRGAh1$$kQLX0lwsJLBfIhfHf1kzD",
      "component" : "Reformat",
      "metadata" : {
        "label" : "Reformat_1",
        "slug" : "Reformat_1",
        "x" : 908.3,
        "y" : 210.00000000000006,
        "language" : "python",
        "phase" : 0,
        "cache" : false,
        "detailedStats" : false,
        "isImported" : false
      },
      "ports" : {
        "inputs" : [ {
          "id" : "mqaOUPDJE_ADROKSWpAkf$$MEslioeZBYwVZF3kdgf04",
          "slug" : "in0"
        } ],
        "outputs" : [ {
          "id" : "lG7Ij5kEpCXIPRklmewCq$$Etg4Ll5zrdPLNUEVQRzFS",
          "slug" : "out"
        } ],
        "selectedInputFields" : [ ],
        "isCustomOutputSchema" : false
      },
      "properties" : {
        "columnsSelector" : [ ],
        "expressions" : [ ]
      }
    },
    "1We4nap3dEhZx6jjdSw6u$$wfYl839GDVV8zzysC92rk" : {
      "id" : "1We4nap3dEhZx6jjdSw6u$$wfYl839GDVV8zzysC92rk",
      "component" : "Aggregate",
      "metadata" : {
        "label" : "Aggregate_2",
        "slug" : "Aggregate_2",
        "x" : 1083.2999999999997,
        "y" : 199.00000000000003,
        "language" : "python",
        "phase" : 0,
        "cache" : false,
        "detailedStats" : false,
        "isImported" : false
      },
      "ports" : {
        "inputs" : [ {
          "id" : "93T_Zw67QiXsuEhY3ApeY$$GEvLmT4bD7S5A0Ohpy95N",
          "slug" : "in0"
        } ],
        "outputs" : [ {
          "id" : "MRUyDBUS0qgyLUkBI_s5m$$lQY_DepJ0XJVmoEGHNBQr",
          "slug" : "out"
        } ],
        "selectedInputFields" : [ ],
        "isCustomOutputSchema" : false
      },
      "properties" : {
        "allIns" : false,
        "doPivot" : false,
        "aggregate" : [ {
          "target" : "count",
          "expression" : {
            "format" : "sql",
            "expression" : "count(1)"
          },
          "description" : "",
          "_row_id" : ""
        } ],
        "pivotColumn" : null,
        "pivotValues" : [ ],
        "activeTab" : "aggregate",
        "columnsSelector" : [ "93T_Zw67QiXsuEhY3ApeY$$GEvLmT4bD7S5A0Ohpy95N##zip" ],
        "groupBy" : [ {
          "target" : "zip",
          "expression" : {
            "format" : "sql",
            "expression" : "zip"
          },
          "description" : "",
          "_row_id" : null
        } ]
      }
    },
    "H4qeKZuWDPLa5xc8Ze_-S$$RP_O-g7nIFI-SH4PT-Tkx" : {
      "id" : "H4qeKZuWDPLa5xc8Ze_-S$$RP_O-g7nIFI-SH4PT-Tkx",
      "component" : "Target",
      "metadata" : {
        "label" : "Target_2",
        "slug" : "Target_2",
        "x" : 1480.0500000000002,
        "y" : 676.0999999999999,
        "language" : "python",
        "phase" : 0,
        "cache" : false,
        "detailedStats" : false,
        "isImported" : false
      },
      "ports" : {
        "inputs" : [ {
          "id" : "mB-uZB0ld2WC6LuApYt9p$$ntncYtMS8Zo2P9vamjLb9",
          "slug" : "in0"
        } ],
        "outputs" : [ ],
        "selectedInputFields" : [ ],
        "isCustomOutputSchema" : false
      },
      "properties" : {
        "datasetId" : "1700/datasets/zip_delta_table"
      }
    },
    "LqTTU_Ra4CXT7mwQJnGGS$$VSAqz4qDtlkjt-kMoFlYM" : {
      "id" : "LqTTU_Ra4CXT7mwQJnGGS$$VSAqz4qDtlkjt-kMoFlYM",
      "component" : "Reformat",
      "metadata" : {
        "label" : "Reformat_5",
        "slug" : "Reformat_5",
        "x" : 796.8250000000002,
        "y" : 672.15,
        "language" : "python",
        "phase" : 0,
        "cache" : false,
        "detailedStats" : false,
        "isImported" : false
      },
      "ports" : {
        "inputs" : [ {
          "id" : "O1fBdsvrjWl1FU6vAvnur$$UAwatZ9YI1kQpvG85BYtM",
          "slug" : "in0"
        } ],
        "outputs" : [ {
          "id" : "GPWfwdfNVB7IQaSFRcY_G$$9vDuUBGv6OHIEjy3htNsa",
          "slug" : "out"
        } ],
        "selectedInputFields" : [ ],
        "isCustomOutputSchema" : false
      },
      "properties" : {
        "columnsSelector" : [ "O1fBdsvrjWl1FU6vAvnur$$UAwatZ9YI1kQpvG85BYtM##zipcode" ],
        "expressions" : [ {
          "target" : "zip_count",
          "expression" : {
            "format" : "sql",
            "expression" : "sum(if(zipcode != '00000' and zipcode != '99999', 1, 0))"
          },
          "description" : ""
        } ]
      }
    },
    "_GiFXBzO_NnB4iIsyRM0T$$V8hemfRGNZuQVK4vHELdK" : {
      "id" : "_GiFXBzO_NnB4iIsyRM0T$$V8hemfRGNZuQVK4vHELdK",
      "component" : "Source",
      "metadata" : {
        "label" : "IrsZipcodesSource",
        "slug" : "IrsZipcodesSource",
        "x" : 469,
        "y" : 511,
        "language" : "python",
        "phase" : 0,
        "cache" : false,
        "detailedStats" : false,
        "isImported" : false
      },
      "ports" : {
        "inputs" : [ ],
        "outputs" : [ {
          "id" : "ASJRyxNpCf6bMQdv5RZh1$$s58ROYh4qPn1zeTNghc6q",
          "slug" : "out"
        } ],
        "selectedInputFields" : [ ],
        "isCustomOutputSchema" : false
      },
      "properties" : {
        "datasetId" : "1700/datasets/irs-zipcode-data"
      }
    },
    "BKfj7FhwIUo51cPDED1cV$$ERdTXAT-w1Yun4TCeHWOy" : {
      "id" : "BKfj7FhwIUo51cPDED1cV$$ERdTXAT-w1Yun4TCeHWOy",
      "component" : "Reformat",
      "metadata" : {
        "label" : "Reformat_4",
        "slug" : "Reformat_4",
        "x" : 1251.3000000000002,
        "y" : 202.00000000000014,
        "language" : "python",
        "phase" : 0,
        "cache" : false,
        "detailedStats" : false,
        "isImported" : false
      },
      "ports" : {
        "inputs" : [ {
          "id" : "siHiegQWwyVZNHVnS1StX$$xjDz2VyuAxzke47tLAtD5",
          "slug" : "in0"
        } ],
        "outputs" : [ {
          "id" : "XjOtRumsTMo4tGhv-GkXW$$SyUs2MidMLwcHwbche4b2",
          "slug" : "out"
        } ],
        "selectedInputFields" : [ ],
        "isCustomOutputSchema" : false
      },
      "properties" : {
        "columnsSelector" : [ ],
        "expressions" : [ ]
      }
    },
    "bpXu-Hun__7xIF_ykAqNA$$LrzKw7EPIzlJ9wMkK8cz1" : {
      "id" : "bpXu-Hun__7xIF_ykAqNA$$LrzKw7EPIzlJ9wMkK8cz1",
      "component" : "Aggregate",
      "metadata" : {
        "label" : "Aggregate_1",
        "slug" : "Aggregate_1",
        "x" : 931.3000000000001,
        "y" : 440.00000000000006,
        "language" : "python",
        "phase" : 0,
        "cache" : false,
        "detailedStats" : false,
        "isImported" : false
      },
      "ports" : {
        "inputs" : [ {
          "id" : "GSKYD4-HPLz-kWKlzwT2g$$KOxmJHOOzzPO4BJYP-lxp",
          "slug" : "in0"
        } ],
        "outputs" : [ {
          "id" : "Tzk3MdIhZx3ETbh1nfEYz$$fa1TBFNkhPpBZati5Zuca",
          "slug" : "out"
        } ],
        "selectedInputFields" : [ ],
        "isCustomOutputSchema" : false
      },
      "properties" : {
        "allIns" : false,
        "doPivot" : false,
        "aggregate" : [ {
          "target" : "count",
          "expression" : {
            "format" : "sql",
            "expression" : "count(1)"
          },
          "description" : "",
          "_row_id" : ""
        } ],
        "pivotColumn" : null,
        "pivotValues" : [ ],
        "activeTab" : "aggregate",
        "columnsSelector" : [ "GSKYD4-HPLz-kWKlzwT2g$$KOxmJHOOzzPO4BJYP-lxp##zipcode" ],
        "groupBy" : [ {
          "target" : "zipcode",
          "expression" : {
            "format" : "sql",
            "expression" : "zipcode"
          },
          "description" : "",
          "_row_id" : null
        } ]
      }
    },
    "cwGenY4Qa5QOIhzy14O0R$$pgJniJ2bYsvfJaNOxbae5" : {
      "id" : "cwGenY4Qa5QOIhzy14O0R$$pgJniJ2bYsvfJaNOxbae5",
      "component" : "Target",
      "metadata" : {
        "label" : "Target_1",
        "slug" : "Target_1",
        "x" : 1486.4500000000003,
        "y" : 470.9,
        "language" : "python",
        "phase" : 0,
        "cache" : false,
        "detailedStats" : false,
        "isImported" : false
      },
      "ports" : {
        "inputs" : [ {
          "id" : "Ma2Cgxy1KRJQ5cRs6lAsh$$L31qIcSVrbn4zgZvrOtUe",
          "slug" : "in0"
        } ],
        "outputs" : [ ],
        "selectedInputFields" : [ ],
        "isCustomOutputSchema" : false
      },
      "properties" : {
        "datasetId" : "1700/datasets/zip_delta"
      }
    }
  },
  "ports" : {
    "inputs" : [ ],
    "outputs" : [ ],
    "selectedInputFields" : [ ],
    "isCustomOutputSchema" : false
  }
}